LICENSE
MANIFEST.in
README.rst
setup.py
automationcommon/__init__.py
automationcommon/admin.py
automationcommon/middleware.py
automationcommon/models.py
automationcommon/urls.py
automationcommon/utils.py
automationcommon/views.py
automationcommon/migrations/0001_initial.py
automationcommon/migrations/__init__.py
automationcommon/static/css/hijack-styles.css
automationcommon/templates/impersonate.html
automationcommon/templates/status.html
automationcommon/templatetags/__init__.py
automationcommon/templatetags/custom_filters.py
automationcommon/templatetags/custom_tags.py
automationcommon/tests/__init__.py
automationcommon/tests/test_models.py
automationcommon/tests/test_templatetags_custom_filters.py
automationcommon/tests/test_utils.py
automationcommon/tests/utils.py
django_automationcommon.egg-info/PKG-INFO
django_automationcommon.egg-info/SOURCES.txt
django_automationcommon.egg-info/dependency_links.txt
django_automationcommon.egg-info/requires.txt
django_automationcommon.egg-info/top_level.txt