Metadata-Version: 1.1
Name: django-automationcommon
Version: 1.12
Summary: Common functionality across different Django projects of the UofC UIS Automation team
Home-page: https://git.csx.cam.ac.uk/i/ucs/automation/django-automationcommon
Author: Automation team, University Information Services, University of Cambridge
Author-email: automation@uis.cam.ac.uk
License: MIT
Platform: UNKNOWN
Classifier: Development Status :: 5 - Production/Stable
Classifier: Environment :: Web Environment
Classifier: Framework :: Django
Classifier: Intended Audience :: Developers
Classifier: License :: OSI Approved :: MIT License
Classifier: Operating System :: OS Independent
Classifier: Programming Language :: Python
